{
  "data": {
    "article": {},
    "attachments": {
      "media_keys": [
        "3_1866765722938118144"
      ],
      "media_source_tweet_id": [
        "1866765726809460911"
      ]
    },
    "author_id": "1081115542109380608",
    "conversation_id": "1866782444067987937",
    "created_at": "2024-12-11T09:49:52.000Z",
    "edit_controls": {
      "editable_until": "2024-12-11T10:49:52.000Z",
      "edits_remaining": 5,
      "is_edit_eligible": false
    },
    "edit_history_tweet_ids": [
      "1866782444067987937"
    ],
    "entities": {
      "hashtags": [
        {
          "end": 23,
          "start": 13,
          "tag": "AveMujica"
        },
        {
          "end": 29,
          "start": 24,
          "tag": "豐川祥子"
        }
      ],
      "mentions": [
        {
          "end": 11,
          "id": "1515904769809813504",
          "start": 3,
          "username": "yu_Wyan"
        }
      ],
      "urls": [
        {
          "display_url": "pic.x.com/VPmfosf2xG",
          "end": 53,
          "expanded_url": "https://x.com/yu_Wyan/status/1866765726809460911/photo/1",
          "media_key": "3_1866765722938118144",
          "start": 30,
          "url": "https://t.co/VPmfosf2xG"
        }
      ]
    },
    "geo": {},
    "id": "1866782444067987937",
    "lang": "qme",
    "note_tweet": {
      "entities": {}
    },
    "possibly_sensitive": false,
    "public_metrics": {
      "bookmark_count": 0,
      "impression_count": 0,
      "like_count": 0,
      "quote_count": 0,
      "reply_count": 0,
      "retweet_count": 8
    },
    "referenced_tweets": [
      {
        "id": "1866765726809460911",
        "type": "retweeted"
      }
    ],
    "reply_settings": "everyone",
    "text": "RT @yu_Wyan: #AveMujica #豐川祥子 https://t.co/VPmfosf2xG"
  },
  "includes": {
    "media": [
      {
        "height": 2048,
        "media_key": "3_1866765722938118144",
        "public_metrics": {},
        "type": "photo",
        "url": "https://pbs.twimg.com/media/GegViNKaEAAwJxP.jpg",
        "width": 2048
      }
    ],
    "tweets": [
      {
        "article": {},
        "attachments": {
          "media_keys": [
            "3_1866765722938118144"
          ],
          "media_source_tweet_id": [
            "1866765726809460911"
          ]
        },
        "author_id": "1081115542109380608",
        "conversation_id": "1866782444067987937",
        "created_at": "2024-12-11T09:49:52.000Z",
        "edit_controls": {
          "editable_until": "2024-12-11T10:49:52.000Z",
          "edits_remaining": 5,
          "is_edit_eligible": false
        },
        "edit_history_tweet_ids": [
          "1866782444067987937"
        ],
        "entities": {
          "hashtags": [
            {
              "end": 23,
              "start": 13,
              "tag": "AveMujica"
            },
            {
              "end": 29,
              "start": 24,
              "tag": "豐川祥子"
            }
          ],
          "mentions": [
            {
              "end": 11,
              "id": "1515904769809813504",
              "start": 3,
              "username": "yu_Wyan"
            }
          ],
          "urls": [
            {
              "display_url": "pic.x.com/VPmfosf2xG",
              "end": 53,
              "expanded_url": "https://x.com/yu_Wyan/status/1866765726809460911/photo/1",
              "media_key": "3_1866765722938118144",
              "start": 30,
              "url": "https://t.co/VPmfosf2xG"
            }
          ]
        },
        "geo": {},
        "id": "1866782444067987937",
        "lang": "qme",
        "note_tweet": {
          "entities": {}
        },
        "possibly_sensitive": false,
        "public_metrics": {
          "bookmark_count": 0,
          "impression_count": 0,
          "like_count": 0,
          "quote_count": 0,
          "reply_count": 0,
          "retweet_count": 8
        },
        "referenced_tweets": [
          {
            "id": "1866765726809460911",
            "type": "retweeted"
          }
        ],
        "reply_settings": "everyone",
        "text": "RT @yu_Wyan: #AveMujica #豐川祥子 https://t.co/VPmfosf2xG"
      },
      {
        "article": {},
        "attachments": {
          "media_keys": [
            "3_1866765722938118144"
          ]
        },
        "author_id": "1515904769809813504",
        "conversation_id": "1866765726809460911",
        "created_at": "2024-12-11T08:43:26.000Z",
        "edit_controls": {
          "editable_until": "2024-12-11T09:43:26.000Z",
          "edits_remaining": 5,
          "is_edit_eligible": true
        },
        "edit_history_tweet_ids": [
          "1866765726809460911"
        ],
        "entities": {
          "hashtags": [
            {
              "end": 10,
              "start": 0,
              "tag": "AveMujica"
            },
            {
              "end": 16,
              "start": 11,
              "tag": "豐川祥子"
            }
          ],
          "urls": [
            {
              "display_url": "pic.x.com/VPmfosf2xG",
              "end": 40,
              "expanded_url": "https://x.com/yu_Wyan/status/1866765726809460911/photo/1",
              "media_key": "3_1866765722938118144",
              "start": 17,
              "url": "https://t.co/VPmfosf2xG"
            }
          ]
        },
        "geo": {},
        "id": "1866765726809460911",
        "lang": "qme",
        "note_tweet": {
          "entities": {}
        },
        "possibly_sensitive": false,
        "public_metrics": {
          "bookmark_count": 6,
          "impression_count": 349,
          "like_count": 48,
          "quote_count": 0,
          "reply_count": 0,
          "retweet_count": 8
        },
        "reply_settings": "everyone",
        "text": "#AveMujica #豐川祥子 https://t.co/VPmfosf2xG"
      }
    ],
    "users": [
      {
        "created_at": "2019-01-04T09:10:06.000Z",
        "description": "",
        "id": "1081115542109380608",
        "name": "RyougiShiki",
        "pinned_tweet_id": "1863983459905237429",
        "profile_image_url": "https://pbs.twimg.com/profile_images/1864333689951539204/7SF8ek5x_normal.jpg",
        "protected": false,
        "public_metrics": {
          "followers_count": 13,
          "following_count": 147,
          "like_count": 5846,
          "listed_count": 0,
          "media_count": 16,
          "tweet_count": 1023
        },
        "username": "damniwokeup",
        "verified": false
      },
      {
        "created_at": "2022-04-18T04:07:29.000Z",
        "description": "🇭🇰→🇨🇦/I draw something /雜多/ Eng&中👌🏻/all🎼",
        "entities": {
          "url": {
            "urls": [
              {
                "display_url": "instagram.com/yu_wyan?igshid…",
                "end": 23,
                "expanded_url": "https://instagram.com/yu_wyan?igshid=YWJhMjlhZTc=",
                "start": 0,
                "url": "https://t.co/iyxOzNOVgf"
              }
            ]
          }
        },
        "id": "1515904769809813504",
        "location": "女同妙妙屋",
        "name": "帷煙Y",
        "pinned_tweet_id": "1745730829647757818",
        "profile_image_url": "https://pbs.twimg.com/profile_images/1838041575974182912/aQ9N65bC_normal.jpg",
        "protected": false,
        "public_metrics": {
          "followers_count": 2719,
          "following_count": 22,
          "like_count": 179,
          "listed_count": 15,
          "media_count": 81,
          "tweet_count": 140
        },
        "url": "https://t.co/iyxOzNOVgf",
        "username": "yu_Wyan",
        "verified": false
      }
    ]
  }
}