{
  "data": {
    "article": {},
    "attachments": {
      "media_keys": [
        "3_1871295739692974081",
        "3_1871295739692978176",
        "3_1871295739697221633",
        "3_1871295739697180672"
      ],
      "media_source_tweet_id": [
        "1871295745997127691",
        "1871295745997127691",
        "1871295745997127691",
        "1871295745997127691"
      ]
    },
    "author_id": "1081115542109380608",
    "conversation_id": "1871366463887675397",
    "created_at": "2024-12-24T01:25:07.000Z",
    "edit_controls": {
      "editable_until": "2024-12-24T02:25:07.000Z",
      "edits_remaining": 5,
      "is_edit_eligible": false
    },
    "edit_history_tweet_ids": [
      "1871366463887675397"
    ],
    "entities": {
      "hashtags": [
        {
          "end": 24,
          "start": 13,
          "tag": "ガールズバンドクライ"
        },
        {
          "end": 38,
          "start": 25,
          "tag": "GirlsBandCry"
        }
      ],
      "mentions": [
        {
          "end": 11,
          "id": "1082862022453121024",
          "start": 3,
          "username": "Yumuto5"
        }
      ],
      "urls": [
        {
          "display_url": "pic.x.com/M55vDjfyl1",
          "end": 78,
          "expanded_url": "https://x.com/Yumuto5/status/1871295745997127691/photo/1",
          "media_key": "3_1871295739692974081",
          "start": 55,
          "url": "https://t.co/M55vDjfyl1"
        },
        {
          "display_url": "pic.x.com/M55vDjfyl1",
          "end": 78,
          "expanded_url": "https://x.com/Yumuto5/status/1871295745997127691/photo/1",
          "media_key": "3_1871295739692978176",
          "start": 55,
          "url": "https://t.co/M55vDjfyl1"
        },
        {
          "display_url": "pic.x.com/M55vDjfyl1",
          "end": 78,
          "expanded_url": "https://x.com/Yumuto5/status/1871295745997127691/photo/1",
          "media_key": "3_1871295739697221633",
          "start": 55,
          "url": "https://t.co/M55vDjfyl1"
        },
        {
          "display_url": "pic.x.com/M55vDjfyl1",
          "end": 78,
          "expanded_url": "https://x.com/Yumuto5/status/1871295745997127691/photo/1",
          "media_key": "3_1871295739697180672",
          "start": 55,
          "url": "https://t.co/M55vDjfyl1"
        }
      ]
    },
    "geo": {},
    "id": "1871366463887675397",
    "lang": "und",
    "note_tweet": {
      "entities": {}
    },
    "possibly_sensitive": false,
    "public_metrics": {
      "bookmark_count": 0,
      "impression_count": 0,
      "like_count": 0,
      "quote_count": 0,
      "reply_count": 0,
      "retweet_count": 202
    },
    "referenced_tweets": [
      {
        "id": "1871295745997127691",
        "type": "retweeted"
      }
    ],
    "reply_settings": "everyone",
    "text": "RT @Yumuto5: #ガールズバンドクライ #GirlsBandCry \nkwiiiiiiiiiiii https://t.co/M55vDjfyl1"
  },
  "includes": {
    "media": [
      {
        "height": 1444,
        "media_key": "3_1871295739692974081",
        "public_metrics": {},
        "type": "photo",
        "url": "https://pbs.twimg.com/media/Gfgtj4oaAAEIyXN.jpg",
        "width": 2048
      },
      {
        "height": 244,
        "media_key": "3_1871295739692978176",
        "public_metrics": {},
        "type": "photo",
        "url": "https://pbs.twimg.com/media/Gfgtj4oaEAA5oRD.jpg",
        "width": 528
      },
      {
        "height": 1592,
        "media_key": "3_1871295739697221633",
        "public_metrics": {},
        "type": "photo",
        "url": "https://pbs.twimg.com/media/Gfgtj4pa0AE7CBz.jpg",
        "width": 1358
      },
      {
        "height": 1592,
        "media_key": "3_1871295739697180672",
        "public_metrics": {},
        "type": "photo",
        "url": "https://pbs.twimg.com/media/Gfgtj4paMAAcn6e.jpg",
        "width": 1358
      }
    ],
    "tweets": [
      {
        "article": {},
        "attachments": {
          "media_keys": [
            "3_1871295739692974081",
            "3_1871295739692978176",
            "3_1871295739697221633",
            "3_1871295739697180672"
          ],
          "media_source_tweet_id": [
            "1871295745997127691",
            "1871295745997127691",
            "1871295745997127691",
            "1871295745997127691"
          ]
        },
        "author_id": "1081115542109380608",
        "conversation_id": "1871366463887675397",
        "created_at": "2024-12-24T01:25:07.000Z",
        "edit_controls": {
          "editable_until": "2024-12-24T02:25:07.000Z",
          "edits_remaining": 5,
          "is_edit_eligible": false
        },
        "edit_history_tweet_ids": [
          "1871366463887675397"
        ],
        "entities": {
          "hashtags": [
            {
              "end": 24,
              "start": 13,
              "tag": "ガールズバンドクライ"
            },
            {
              "end": 38,
              "start": 25,
              "tag": "GirlsBandCry"
            }
          ],
          "mentions": [
            {
              "end": 11,
              "id": "1082862022453121024",
              "start": 3,
              "username": "Yumuto5"
            }
          ],
          "urls": [
            {
              "display_url": "pic.x.com/M55vDjfyl1",
              "end": 78,
              "expanded_url": "https://x.com/Yumuto5/status/1871295745997127691/photo/1",
              "media_key": "3_1871295739692974081",
              "start": 55,
              "url": "https://t.co/M55vDjfyl1"
            },
            {
              "display_url": "pic.x.com/M55vDjfyl1",
              "end": 78,
              "expanded_url": "https://x.com/Yumuto5/status/1871295745997127691/photo/1",
              "media_key": "3_1871295739692978176",
              "start": 55,
              "url": "https://t.co/M55vDjfyl1"
            },
            {
              "display_url": "pic.x.com/M55vDjfyl1",
              "end": 78,
              "expanded_url": "https://x.com/Yumuto5/status/1871295745997127691/photo/1",
              "media_key": "3_1871295739697221633",
              "start": 55,
              "url": "https://t.co/M55vDjfyl1"
            },
            {
              "display_url": "pic.x.com/M55vDjfyl1",
              "end": 78,
              "expanded_url": "https://x.com/Yumuto5/status/1871295745997127691/photo/1",
              "media_key": "3_1871295739697180672",
              "start": 55,
              "url": "https://t.co/M55vDjfyl1"
            }
          ]
        },
        "geo": {},
        "id": "1871366463887675397",
        "lang": "und",
        "note_tweet": {
          "entities": {}
        },
        "possibly_sensitive": false,
        "public_metrics": {
          "bookmark_count": 0,
          "impression_count": 0,
          "like_count": 0,
          "quote_count": 0,
          "reply_count": 0,
          "retweet_count": 202
        },
        "referenced_tweets": [
          {
            "id": "1871295745997127691",
            "type": "retweeted"
          }
        ],
        "reply_settings": "everyone",
        "text": "RT @Yumuto5: #ガールズバンドクライ #GirlsBandCry \nkwiiiiiiiiiiii https://t.co/M55vDjfyl1"
      },
      {
        "article": {},
        "attachments": {
          "media_keys": [
            "3_1871295739692974081",
            "3_1871295739692978176",
            "3_1871295739697221633",
            "3_1871295739697180672"
          ]
        },
        "author_id": "1082862022453121024",
        "conversation_id": "1871295745997127691",
        "created_at": "2024-12-23T20:44:07.000Z",
        "edit_controls": {
          "editable_until": "2024-12-23T21:44:07.000Z",
          "edits_remaining": 5,
          "is_edit_eligible": true
        },
        "edit_history_tweet_ids": [
          "1871295745997127691"
        ],
        "entities": {
          "hashtags": [
            {
              "end": 11,
              "start": 0,
              "tag": "ガールズバンドクライ"
            },
            {
              "end": 25,
              "start": 12,
              "tag": "GirlsBandCry"
            }
          ],
          "urls": [
            {
              "display_url": "pic.x.com/M55vDjfyl1",
              "end": 65,
              "expanded_url": "https://x.com/Yumuto5/status/1871295745997127691/photo/1",
              "media_key": "3_1871295739692974081",
              "start": 42,
              "url": "https://t.co/M55vDjfyl1"
            },
            {
              "display_url": "pic.x.com/M55vDjfyl1",
              "end": 65,
              "expanded_url": "https://x.com/Yumuto5/status/1871295745997127691/photo/1",
              "media_key": "3_1871295739692978176",
              "start": 42,
              "url": "https://t.co/M55vDjfyl1"
            },
            {
              "display_url": "pic.x.com/M55vDjfyl1",
              "end": 65,
              "expanded_url": "https://x.com/Yumuto5/status/1871295745997127691/photo/1",
              "media_key": "3_1871295739697221633",
              "start": 42,
              "url": "https://t.co/M55vDjfyl1"
            },
            {
              "display_url": "pic.x.com/M55vDjfyl1",
              "end": 65,
              "expanded_url": "https://x.com/Yumuto5/status/1871295745997127691/photo/1",
              "media_key": "3_1871295739697180672",
              "start": 42,
              "url": "https://t.co/M55vDjfyl1"
            }
          ]
        },
        "geo": {},
        "id": "1871295745997127691",
        "lang": "und",
        "note_tweet": {
          "entities": {}
        },
        "possibly_sensitive": false,
        "public_metrics": {
          "bookmark_count": 111,
          "impression_count": 11633,
          "like_count": 1084,
          "quote_count": 0,
          "reply_count": 0,
          "retweet_count": 202
        },
        "reply_settings": "everyone",
        "text": "#ガールズバンドクライ #GirlsBandCry \nkwiiiiiiiiiiii https://t.co/M55vDjfyl1"
      }
    ],
    "users": [
      {
        "created_at": "2019-01-04T09:10:06.000Z",
        "description": "",
        "id": "1081115542109380608",
        "name": "RyougiShiki",
        "pinned_tweet_id": "1863983459905237429",
        "profile_image_url": "https://pbs.twimg.com/profile_images/1864333689951539204/7SF8ek5x_normal.jpg",
        "protected": false,
        "public_metrics": {
          "followers_count": 13,
          "following_count": 148,
          "like_count": 6295,
          "listed_count": 0,
          "media_count": 19,
          "tweet_count": 1184
        },
        "username": "damniwokeup",
        "verified": false
      },
      {
        "created_at": "2019-01-09T04:49:59.000Z",
        "description": "⭐星詠み⭐  ガルクラ🎵「中国語注意」",
        "id": "1082862022453121024",
        "name": "Yumuto",
        "pinned_tweet_id": "1807276895039357189",
        "profile_image_url": "https://pbs.twimg.com/profile_images/1868855173529190404/nIiPl5Aa_normal.jpg",
        "protected": false,
        "public_metrics": {
          "followers_count": 11231,
          "following_count": 752,
          "like_count": 2792,
          "listed_count": 86,
          "media_count": 127,
          "tweet_count": 1112
        },
        "username": "Yumuto5",
        "verified": false
      }
    ]
  }
}