{
  "data": {
    "article": {},
    "attachments": {
      "media_keys": [
        "3_1874014309107572736",
        "3_1874014309103329280",
        "3_1874014309640208384"
      ],
      "media_source_tweet_id": [
        "1874014369392320543",
        "1874014369392320543",
        "1874014369392320543"
      ]
    },
    "author_id": "1081115542109380608",
    "conversation_id": "1874024018644476070",
    "created_at": "2024-12-31T09:25:18.000Z",
    "edit_controls": {
      "editable_until": "2024-12-31T10:25:18.000Z",
      "edits_remaining": 5,
      "is_edit_eligible": false
    },
    "edit_history_tweet_ids": [
      "1874024018644476070"
    ],
    "entities": {
      "mentions": [
        {
          "end": 9,
          "id": "1480478198010085377",
          "start": 3,
          "username": "IwZry"
        }
      ],
      "urls": [
        {
          "display_url": "pic.x.com/DWl1N4PeF6",
          "end": 39,
          "expanded_url": "https://x.com/IwZry/status/1874014369392320543/photo/1",
          "media_key": "3_1874014309107572736",
          "start": 16,
          "url": "https://t.co/DWl1N4PeF6"
        },
        {
          "display_url": "pic.x.com/DWl1N4PeF6",
          "end": 39,
          "expanded_url": "https://x.com/IwZry/status/1874014369392320543/photo/1",
          "media_key": "3_1874014309103329280",
          "start": 16,
          "url": "https://t.co/DWl1N4PeF6"
        },
        {
          "display_url": "pic.x.com/DWl1N4PeF6",
          "end": 39,
          "expanded_url": "https://x.com/IwZry/status/1874014369392320543/photo/1",
          "media_key": "3_1874014309640208384",
          "start": 16,
          "url": "https://t.co/DWl1N4PeF6"
        }
      ]
    },
    "geo": {},
    "id": "1874024018644476070",
    "lang": "und",
    "note_tweet": {
      "entities": {}
    },
    "possibly_sensitive": false,
    "public_metrics": {
      "bookmark_count": 0,
      "impression_count": 0,
      "like_count": 0,
      "quote_count": 0,
      "reply_count": 0,
      "retweet_count": 146
    },
    "referenced_tweets": [
      {
        "id": "1874014369392320543",
        "type": "retweeted"
      }
    ],
    "reply_settings": "everyone",
    "text": "RT @IwZry: 2024 https://t.co/DWl1N4PeF6"
  },
  "includes": {
    "media": [
      {
        "height": 1024,
        "media_key": "3_1874014309107572736",
        "public_metrics": {},
        "type": "photo",
        "url": "https://pbs.twimg.com/media/GgHWFc5bIAAC4fB.jpg",
        "width": 720
      },
      {
        "height": 1024,
        "media_key": "3_1874014309103329280",
        "public_metrics": {},
        "type": "photo",
        "url": "https://pbs.twimg.com/media/GgHWFc4aYAA6WP3.jpg",
        "width": 656
      },
      {
        "height": 696,
        "media_key": "3_1874014309640208384",
        "public_metrics": {},
        "type": "photo",
        "url": "https://pbs.twimg.com/media/GgHWFe4agAABT-C.jpg",
        "width": 1024
      }
    ],
    "tweets": [
      {
        "article": {},
        "attachments": {
          "media_keys": [
            "3_1874014309107572736",
            "3_1874014309103329280",
            "3_1874014309640208384"
          ],
          "media_source_tweet_id": [
            "1874014369392320543",
            "1874014369392320543",
            "1874014369392320543"
          ]
        },
        "author_id": "1081115542109380608",
        "conversation_id": "1874024018644476070",
        "created_at": "2024-12-31T09:25:18.000Z",
        "edit_controls": {
          "editable_until": "2024-12-31T10:25:18.000Z",
          "edits_remaining": 5,
          "is_edit_eligible": false
        },
        "edit_history_tweet_ids": [
          "1874024018644476070"
        ],
        "entities": {
          "mentions": [
            {
              "end": 9,
              "id": "1480478198010085377",
              "start": 3,
              "username": "IwZry"
            }
          ],
          "urls": [
            {
              "display_url": "pic.x.com/DWl1N4PeF6",
              "end": 39,
              "expanded_url": "https://x.com/IwZry/status/1874014369392320543/photo/1",
              "media_key": "3_1874014309107572736",
              "start": 16,
              "url": "https://t.co/DWl1N4PeF6"
            },
            {
              "display_url": "pic.x.com/DWl1N4PeF6",
              "end": 39,
              "expanded_url": "https://x.com/IwZry/status/1874014369392320543/photo/1",
              "media_key": "3_1874014309103329280",
              "start": 16,
              "url": "https://t.co/DWl1N4PeF6"
            },
            {
              "display_url": "pic.x.com/DWl1N4PeF6",
              "end": 39,
              "expanded_url": "https://x.com/IwZry/status/1874014369392320543/photo/1",
              "media_key": "3_1874014309640208384",
              "start": 16,
              "url": "https://t.co/DWl1N4PeF6"
            }
          ]
        },
        "geo": {},
        "id": "1874024018644476070",
        "lang": "und",
        "note_tweet": {
          "entities": {}
        },
        "possibly_sensitive": false,
        "public_metrics": {
          "bookmark_count": 0,
          "impression_count": 0,
          "like_count": 0,
          "quote_count": 0,
          "reply_count": 0,
          "retweet_count": 146
        },
        "referenced_tweets": [
          {
            "id": "1874014369392320543",
            "type": "retweeted"
          }
        ],
        "reply_settings": "everyone",
        "text": "RT @IwZry: 2024 https://t.co/DWl1N4PeF6"
      },
      {
        "article": {},
        "attachments": {
          "media_keys": [
            "3_1874014309107572736",
            "3_1874014309103329280",
            "3_1874014309640208384"
          ]
        },
        "author_id": "1480478198010085377",
        "conversation_id": "1874014369392320543",
        "created_at": "2024-12-31T08:46:57.000Z",
        "edit_controls": {
          "editable_until": "2024-12-31T09:46:57.000Z",
          "edits_remaining": 5,
          "is_edit_eligible": true
        },
        "edit_history_tweet_ids": [
          "1874014369392320543"
        ],
        "entities": {
          "urls": [
            {
              "display_url": "pic.x.com/DWl1N4PeF6",
              "end": 28,
              "expanded_url": "https://x.com/IwZry/status/1874014369392320543/photo/1",
              "media_key": "3_1874014309107572736",
              "start": 5,
              "url": "https://t.co/DWl1N4PeF6"
            },
            {
              "display_url": "pic.x.com/DWl1N4PeF6",
              "end": 28,
              "expanded_url": "https://x.com/IwZry/status/1874014369392320543/photo/1",
              "media_key": "3_1874014309103329280",
              "start": 5,
              "url": "https://t.co/DWl1N4PeF6"
            },
            {
              "display_url": "pic.x.com/DWl1N4PeF6",
              "end": 28,
              "expanded_url": "https://x.com/IwZry/status/1874014369392320543/photo/1",
              "media_key": "3_1874014309640208384",
              "start": 5,
              "url": "https://t.co/DWl1N4PeF6"
            }
          ]
        },
        "geo": {},
        "id": "1874014369392320543",
        "lang": "und",
        "note_tweet": {
          "entities": {}
        },
        "possibly_sensitive": false,
        "public_metrics": {
          "bookmark_count": 146,
          "impression_count": 14101,
          "like_count": 1258,
          "quote_count": 0,
          "reply_count": 0,
          "retweet_count": 146
        },
        "reply_settings": "everyone",
        "text": "2024 https://t.co/DWl1N4PeF6"
      }
    ],
    "users": [
      {
        "created_at": "2019-01-04T09:10:06.000Z",
        "description": "",
        "id": "1081115542109380608",
        "name": "RyougiShiki",
        "pinned_tweet_id": "1863983459905237429",
        "profile_image_url": "https://pbs.twimg.com/profile_images/1873251527508492288/Qw8besei_normal.jpg",
        "protected": false,
        "public_metrics": {
          "followers_count": 14,
          "following_count": 149,
          "like_count": 6474,
          "listed_count": 0,
          "media_count": 20,
          "tweet_count": 1251
        },
        "username": "damniwokeup",
        "verified": false
      },
      {
        "created_at": "2022-01-10T09:54:57.000Z",
        "description": "イラストレーター  22funabashi.hana@gmail.com",
        "entities": {
          "url": {
            "urls": [
              {
                "display_url": "pixiv.net/users/86498240",
                "end": 23,
                "expanded_url": "https://www.pixiv.net/users/86498240",
                "start": 0,
                "url": "https://t.co/ferdzgsZjj"
              }
            ]
          }
        },
        "id": "1480478198010085377",
        "name": "船橋花",
        "pinned_tweet_id": "1608814491504103425",
        "profile_image_url": "https://pbs.twimg.com/profile_images/1490140157722652672/ZoQqLS8b_normal.jpg",
        "protected": false,
        "public_metrics": {
          "followers_count": 114319,
          "following_count": 232,
          "like_count": 2767,
          "listed_count": 985,
          "media_count": 25,
          "tweet_count": 203
        },
        "url": "https://t.co/ferdzgsZjj",
        "username": "IwZry",
        "verified": false
      }
    ]
  }
}